waloviz/__init__.py
waloviz/_bokeh_manipulation.py
waloviz/_holoviews_manipulations.py
waloviz/_panel_manipulation.py
waloviz/_tensor_utils.py
waloviz/_user_functions.py
waloviz/_version.py
waloviz-0.0.1.dist-info/METADATA
waloviz-0.0.1.dist-info/WHEEL
waloviz-0.0.1.dist-info/licenses/LICENSE
waloviz-0.0.1.dist-info/RECORD
