Metadata-Version: 2.3
Name: waloviz
Version: 0.0.1
Summary: An interactive audio player with a spectrogram built-in, as a Jupyter widget or as HTML.
Project-URL: Homepage, https://waloviz.com
Project-URL: Documentation, https://waloviz.com
Project-URL: Repository, https://github.com/AlonKellner/waloviz.git
Author-email: Alon Kellner <me@alonkellner.com>
Maintainer-email: Alon Kellner <me@alonkellner.com>, py@waloviz.com
License-File: LICENSE
Keywords: audio,bokeh,ffmpeg,flac,holoviz,mp3,player,spectrogram,speech,visualization,wav
Classifier: Development Status :: 3 - Alpha
Classifier: Intended Audience :: Science/Research
Classifier: License :: OSI Approved :: MIT License
Classifier: Programming Language :: Python :: 3
Classifier: Topic :: Multimedia :: Sound/Audio :: Analysis
Requires-Python: >=3.8
Requires-Dist: bokeh
Requires-Dist: holoviews
Requires-Dist: numpy
Requires-Dist: panel
Requires-Dist: scipy
Requires-Dist: torch
Requires-Dist: torchaudio
